tolmate/__init__.py
tolmate/example.py
tolmate/test_tolmate.py
tolmate/tmate.py
TolMate-1.0.6.dist-info/LICENSE
TolMate-1.0.6.dist-info/METADATA
TolMate-1.0.6.dist-info/WHEEL
TolMate-1.0.6.dist-info/top_level.txt
TolMate-1.0.6.dist-info/RECORD
