Metadata-Version: 2.1
Name: TolMate
Version: 1.0.6
Summary: TolMate ;-P
Author-email: Samuele Giani <samuele.giani@empa.ch>
Project-URL: Homepage, https://pypi.org/project/tolmate/
Project-URL: Issues, https://pypi.org/project/tolmate/
Classifier: Programming Language :: Python :: 3
Classifier: License :: OSI Approved :: GNU General Public License v3 (GPLv3)
Classifier: Operating System :: OS Independent
Requires-Python: >=3.8
License-File: LICENSE
